hebrew_names/__init__.py
hebrew_names/dist.christian.female.first
hebrew_names/dist.christian.last
hebrew_names/dist.christian.male.first
hebrew_names/dist.cumulatives.all
hebrew_names/dist.druze.female.first
hebrew_names/dist.druze.last
hebrew_names/dist.druze.male.first
hebrew_names/dist.jew.female.first
hebrew_names/dist.jew.last
hebrew_names/dist.jew.male.first
hebrew_names/dist.muslim.female.first
hebrew_names/dist.muslim.last
hebrew_names/dist.muslim.male.first
hebrew_names/dist.other.female.first
hebrew_names/dist.other.last
hebrew_names/dist.other.male.first
hebrew_names/main.py
hebrew_names-0.0.1.dist-info/AUTHORS.rst
hebrew_names-0.0.1.dist-info/LICENSE.txt
hebrew_names-0.0.1.dist-info/METADATA
hebrew_names-0.0.1.dist-info/WHEEL
hebrew_names-0.0.1.dist-info/entry_points.txt
hebrew_names-0.0.1.dist-info/top_level.txt
hebrew_names-0.0.1.dist-info/RECORD
